tests/__init__.py
tests/conftest.py
tests/context.py
tests/mailbox.py
tests/test_cli.py
tests/test_collection.py
tests/test_config.py
tests/test_diff.py
tests/test_email.py
tests/test_notification.py
tests/test_serialization.py
tests/test_watch.py
tests/data/cli.placet
tests/data/sample.yaml
tests/data/xml
vigil/__init__.py
vigil/__main__.py
vigil/cli.py
vigil/collection.py
vigil/config.py
vigil/watch.py
vigil/config/config.yaml
vigil/config/logging.yaml
vigil/locale/cs/LC_MESSAGES/vigil.mo
vigil/locale/en/LC_MESSAGES/vigil.mo
vigil/output/__init__.py
vigil/output/email.py
vigil/output/notification.py
vigil/templates/Email.j2
vigil/templates/Notification.j2
vigil/utils/__init__.py
vigil/utils/diff.py
vigil/utils/logger.py
vigil/utils/serialization.py
vigil_cli-0.3.dist-info/DESCRIPTION.rst
vigil_cli-0.3.dist-info/METADATA
vigil_cli-0.3.dist-info/RECORD
vigil_cli-0.3.dist-info/WHEEL
vigil_cli-0.3.dist-info/dependency_links.txt
vigil_cli-0.3.dist-info/entry_points.txt
vigil_cli-0.3.dist-info/metadata.json
vigil_cli-0.3.dist-info/top_level.txt
